Metadata-Version: 1.0
Name: Sunflower
Version: 1.1.0
Summary: model transcription factor binding to DNA
Home-page: http://www.ebi.ac.uk/~hoffman/software/sunflower/
Author: Michael Hoffman
Author-email: hoffman+sunflower@ebi.ac.uk
License: all rights reserved
Download-URL: http://www.ebi.ac.uk/~hoffman/software/sunflower/Sunflower-1.1.0.tar.gz
Platform: UNKNOWN
Classifier: Development Status :: 2 - Pre-Alpha
Classifier: Environment :: Console
Classifier: Intended Audience :: Science/Research
Classifier: License :: Other/Proprietary License
Classifier: Natural Language :: English
Classifier: Operating System :: POSIX :: Linux
Classifier: Programming Language :: Python
Classifier: Topic :: Scientific/Engineering :: Bio-Informatics
